README.rst
setup.py
pysprites/__init__.py
pysprites/__main__.py
pysprites/pysprites
pysprites/sprites.py
pysprites.egg-info/PKG-INFO
pysprites.egg-info/SOURCES.txt
pysprites.egg-info/dependency_links.txt
pysprites.egg-info/requires.txt
pysprites.egg-info/top_level.txt