Metadata-Version: 1.1
Name: pysprites
Version: 2.0
Summary: A mirco python tools for sprite image, support Photoshop layer data
Home-page: https://github.com/LTaoist/pysprites
Author: Mo Norman
Author-email: ltaoist6@gmail.com
License: MIT
Keywords: sprite images generator png sprites css psd
Platform: UNKNOWN
Classifier: Programming Language :: Python :: 2
Classifier: Programming Language :: Python :: 3
Classifier: Development Status :: 4 - Beta
Classifier: Environment :: Web Environment
Classifier: Intended Audience :: Developers
Classifier: License :: OSI Approved :: MIT License
Classifier: Topic :: Software Development :: Libraries
Classifier: Topic :: Utilities
